hodor.py
hodor-2!0.dist-info/METADATA
hodor-2!0.dist-info/WHEEL
hodor-2!0.dist-info/entry_points.txt
hodor-2!0.dist-info/top_level.txt
hodor-2!0.dist-info/RECORD
