Metadata-Version: 2.1
Name: hodor
Version: 2!0
Summary: hodor!
Home-page: http://github.com/bukzor/hodor
Author: Buck Evan
Author-email: buck.2019@gmail.com
License: hodor
Platform: hodor
